rnaview/__init__.py
rnaview/analysis/__init__.py
rnaview/analysis/features.py
rnaview/analysis/metrics.py
rnaview/core/__init__.py
rnaview/core/modifications.py
rnaview/core/sequence.py
rnaview/core/structure.py
rnaview/data/benchmark/small_rna_benchmark.dbn
rnaview/data/benchmark/trna_benchmark.dbn
rnaview/datasets/__init__.py
rnaview/datasets/benchmark.py
rnaview/integrations/__init__.py
rnaview/integrations/predictors.py
rnaview/integrations/viennarna.py
rnaview/io/__init__.py
rnaview/io/parsers.py
rnaview/io/writers.py
rnaview/utils/__init__.py
rnaview/utils/helpers.py
rnaview/visualization/__init__.py
rnaview/visualization/colors.py
rnaview/visualization/plot2d.py
rnaview/visualization/plot3d.py
rnaview-1.0.1.dist-info/licenses/LICENSE
rnaview-1.0.1.dist-info/METADATA
rnaview-1.0.1.dist-info/WHEEL
rnaview-1.0.1.dist-info/top_level.txt
rnaview-1.0.1.dist-info/RECORD
