Metadata-Version: 2.4
Name: rnaview
Version: 1.0.1
Summary: A comprehensive Python package for RNA structure visualization and analysis
Author-email: RNAview Development Team <rnaview@example.com>
Maintainer-email: RNAview Development Team <rnaview@example.com>
License-Expression: MIT
Project-URL: Homepage, https://github.com/yourusername/rnaview
Project-URL: Documentation, https://rnaview.readthedocs.io
Project-URL: Repository, https://github.com/yourusername/rnaview
Project-URL: Issues, https://github.com/yourusername/rnaview/issues
Project-URL: Changelog, https://github.com/yourusername/rnaview/blob/main/CHANGELOG.md
Keywords: RNA,bioinformatics,structure prediction,visualization,secondary structure,computational biology,molecular biology,structural biology
Classifier: Development Status :: 4 - Beta
Classifier: Intended Audience :: Science/Research
Classifier: Intended Audience :: Developers
Classifier: Operating System :: OS Independent
Classifier: Programming Language :: Python :: 3
Classifier: Programming Language :: Python :: 3.8
Classifier: Programming Language :: Python :: 3.9
Classifier: Programming Language :: Python :: 3.10
Classifier: Programming Language :: Python :: 3.11
Classifier: Programming Language :: Python :: 3.12
Classifier: Topic :: Scientific/Engineering :: Bio-Informatics
Classifier: Topic :: Scientific/Engineering :: Visualization
Classifier: Typing :: Typed
Requires-Python: >=3.8
License-File: LICENSE
Requires-Dist: numpy>=1.20.0
Provides-Extra: visualization
Requires-Dist: matplotlib>=3.5.0; extra == "visualization"
Requires-Dist: plotly>=5.0.0; extra == "visualization"
Requires-Dist: scipy>=1.7.0; extra == "visualization"
Provides-Extra: full
Requires-Dist: matplotlib>=3.5.0; extra == "full"
Requires-Dist: plotly>=5.0.0; extra == "full"
Requires-Dist: scipy>=1.7.0; extra == "full"
Requires-Dist: pandas>=1.3.0; extra == "full"
Requires-Dist: biopython>=1.79; extra == "full"
Provides-Extra: dev
Requires-Dist: pytest>=7.0.0; extra == "dev"
Requires-Dist: pytest-cov>=3.0.0; extra == "dev"
Requires-Dist: black>=22.0.0; extra == "dev"
Requires-Dist: isort>=5.10.0; extra == "dev"
Requires-Dist: mypy>=0.950; extra == "dev"
Requires-Dist: flake8>=4.0.0; extra == "dev"
Requires-Dist: sphinx>=4.5.0; extra == "dev"
Requires-Dist: sphinx-rtd-theme>=1.0.0; extra == "dev"
Requires-Dist: build; extra == "dev"
Requires-Dist: twine; extra == "dev"
Dynamic: license-file
